iriuri/__init__.py
iriuri/re/__init__.py
iriuri/re/rfc3986.py
iriuri/re/rfc3987.py
iriuri/re/rfc6874.py
iriuri/re/rfc8141.py
iriuri-0.0.1.dist-info/LICENSE
iriuri-0.0.1.dist-info/METADATA
iriuri-0.0.1.dist-info/WHEEL
iriuri-0.0.1.dist-info/RECORD
