Metadata-Version: 2.1
Name: iriuri
Version: 0.0.1
Summary: Fully RFC 3986/3987 URI and IRI parsing and manipulation
License: MIT
Author: Henry H. Andrews,
Author-email: handrews@modern-json-schema.com
Requires-Python: >=3.8,<4.0
Classifier: License :: OSI Approved :: MIT License
Classifier: Programming Language :: Python :: 3
Classifier: Programming Language :: Python :: 3.8
Classifier: Programming Language :: Python :: 3.9
Classifier: Programming Language :: Python :: 3.10
Classifier: Programming Language :: Python :: 3.11
Classifier: Programming Language :: Python :: 3.12
